{
  "workbench.colorTheme": "Material Code",
  "material-code.colors": {
    "primary": "#006a60",
    "onPrimary": "#00391f",
    "primaryContainer": "#0c5130",
    "onPrimaryContainer": "#aff2c4",
    "secondary": "#cce8e2",
    "onSecondary": "#213528",
    "secondaryContainer": "#374b3d",
    "onSecondaryContainer": "#d1e8d5",
    "tertiary": "#a3cddb",
    "onTertiary": "#033641",
    "tertiaryContainer": "#214c58",
    "onTertiaryContainer": "#bfe9f8",
    "error": "#ba1a1a",
    "onError": "#690005",
    "errorContainer": "#93000a",
    "onErrorContainer": "#ffdad6",
    "surface": "#0f1511",
    "onSurface": "#dfe4dd",
    "surfaceVariant": "#414942",
    "onSurfaceVariant": "#c0c9c0",
    "outline": "#8a938b",
    "outlineVariant": "#414942",
    "inverseSurface": "#dfe4dd",
    "inverseOnSurface": "#2c322d",
    "inversePrimary": "#2b6a46",
    "primaryForeground": "#ffffff",
    "foreground": "#161d1c",
    "mutedForeground": "#3f4947",
    "background": "#d5dbd9",
    "card": "#e9efed",
    "popover": "#e3eae7",
    "hover": "#dde4e1",
    "border": "#bec9c6",
    "secondaryForeground": "#05201c",
    "errorForeground": "#ffffff",
    "success": "#456179",
    "warning": "#cce8e2",
    "syntax.comment": "#3f4947",
    "syntax.string": "#456179",
    "syntax.keyword": "#006a60",
    "syntax.variable": "#161d1c",
    "syntax.attribute": "#456179",
    "syntax.property": "#4a635f",
    "syntax.function": "#4a635f",
    "syntax.constant": "#456179",
    "syntax.bracket1": "#006a60",
    "syntax.bracket2": "#4a635f",
    "syntax.bracket3": "#456179",
    "syntax.bracket4": "#ba1a1a"
  },
  "editor.fontFamily": "'Source Code Pro', 'Symbols Nerd Font Mono', monospace",
  "editor.fontWeight": "normal",
  "http.proxy": "http://127.0.0.1:2080",
  "material-code.inject": [
    "~/.config/Code/material-code-sharp.css"
  ],
  "workbench.secondarySideBar.defaultVisibility": "hidden",
  "chat.viewTitle.enabled": false,
  "chat.viewWelcome.enabled": false,
  "workbench.editor.empty.hint": "hidden"
}
